CHANGELOG.md
LICENSE
MANIFEST.in
README.md
momo.py
requirements.txt
setup.py
momo.egg-info/PKG-INFO
momo.egg-info/SOURCES.txt
momo.egg-info/dependency_links.txt
momo.egg-info/entry_points.txt
momo.egg-info/not-zip-safe
momo.egg-info/requires.txt
momo.egg-info/top_level.txt